dieke/__init__.py
dieke/carnall89params.xls
dieke/njsymbols.py
dieke/sljcalc.py
dieke/wigner.py
dieke/data/FIT91.for
dieke/data/FIT91sub.for
dieke/data/README.txt
dieke/data/XTAL91.for
dieke/data/XTAL91sub.for
dieke/data/dy3fit.c2v
dieke/data/dy3xtal.d2d
dieke/data/f10mp.dat
dieke/data/f11mp.dat
dieke/data/f12mp.dat
dieke/data/f12mp.dat.broken
dieke/data/f2mp.dat
dieke/data/f2nm.dat
dieke/data/f3mp.dat
dieke/data/f3nm.dat
dieke/data/f4mp.dat
dieke/data/f4nm.dat
dieke/data/f5mp.dat
dieke/data/f5nm.dat
dieke/data/f6mp.dat
dieke/data/f6nm.dat
dieke/data/f7mp.dat
dieke/data/f7nm.dat
dieke/data/f8mp.dat
dieke/data/f9mp.dat
dieke-0.5.0.dist-info/AUTHORS.rst
dieke-0.5.0.dist-info/LICENSE
dieke-0.5.0.dist-info/METADATA
dieke-0.5.0.dist-info/WHEEL
dieke-0.5.0.dist-info/top_level.txt
dieke-0.5.0.dist-info/RECORD
