Metadata-Version: 2.2
Name: dieke
Version: 0.5.0
Summary: Crystal field calculations for the rare earths
Home-page: https://github.com/jevonlongdell/dieke
Author: Jevon Longdell
Author-email: jevon.longdell@gmail.com
Classifier: Programming Language :: Python :: 3
Classifier: Operating System :: OS Independent
License-File: LICENSE
License-File: AUTHORS.rst
Requires-Dist: pandas
Requires-Dist: xlrd
Requires-Dist: numpy
Requires-Dist: scipy
Requires-Dist: matplotlib
Requires-Dist: sympy
Dynamic: author
Dynamic: author-email
Dynamic: classifier
Dynamic: description
Dynamic: home-page
Dynamic: requires-dist
Dynamic: summary
